__init__.py
random_stuff.py
random_stuff-0.1.dist-info/LICENCE.txt
random_stuff-0.1.dist-info/METADATA
random_stuff-0.1.dist-info/WHEEL
random_stuff-0.1.dist-info/top_level.txt
random_stuff-0.1.dist-info/RECORD
