Metadata-Version: 2.1
Name: random_stuff
Version: 0.1
Summary: this is some QoL stuff.
Author-email: minoupower554 <ryan.heinschke2010@gmail.com>
Project-URL: Homepage, https://github.com/minoupower554
Classifier: Programming Language :: Python :: 3
Classifier: License :: OSI Approved :: MIT License
Classifier: Operating System :: OS Independent
Requires-Python: >=3.8
License-File: LICENCE.txt
